gitbrowse/__init__.py
gitbrowse/cli.py
gitbrowse/main.py
gitbrowse/api/__init__.py
gitbrowse/api/github.py
gitbrowse/api/utils.py
gitbrowse/config/__init__.py
gitbrowse/models/__init__.py
gitbrowse/models/file.py
gitbrowse/models/repository.py
gitbrowse/services/__init__.py
gitbrowse/services/downloader.py
gitbrowse/services/network.py
gitbrowse/services/repo.py
gitbrowse/ui/__init__.py
gitbrowse/ui/display.py
gitbrowse/ui/messages.py
gitbrowse/ui/styles.py
gitbrowse/utils/__init__.py
gitbrowse/utils/formatter.py
gitbrowse/utils/system.py
gitbrowser-4.0.3.dist-info/METADATA
gitbrowser-4.0.3.dist-info/WHEEL
gitbrowser-4.0.3.dist-info/entry_points.txt
gitbrowser-4.0.3.dist-info/top_level.txt
gitbrowser-4.0.3.dist-info/RECORD
