Metadata-Version: 2.1
Name: gitbrowser
Version: 4.0.3
Summary: A powerful command-line tool for browsing GitHub repositories
Home-page: https://github.com/SimpleDioney/gitbrowse
Author: SimpleDioney
Author-email: contato@dioneygabriel.com.br
Keywords: github,git,cli,browse,terminal
Classifier: Development Status :: 4 - Beta
Classifier: Environment :: Console
Classifier: Intended Audience :: Developers
Classifier: License :: OSI Approved :: MIT License
Classifier: Operating System :: OS Independent
Classifier: Programming Language :: Python
Classifier: Programming Language :: Python :: 3
Classifier: Programming Language :: Python :: 3.8
Classifier: Programming Language :: Python :: 3.9
Classifier: Programming Language :: Python :: 3.10
Classifier: Topic :: Software Development :: Libraries :: Python Modules
Classifier: Topic :: Utilities
Requires-Python: >=3.8
Requires-Dist: requests>=2.25.0
Requires-Dist: beautifulsoup4>=4.9.3
Requires-Dist: colorama>=0.4.4
Requires-Dist: pygments>=2.7.3
Requires-Dist: rich>=10.0.0
Requires-Dist: tqdm>=4.56.0
Requires-Dist: click>=8.0.0
Provides-Extra: dev
Requires-Dist: pytest>=6.2.2; extra == "dev"
Requires-Dist: black>=21.5b2; extra == "dev"
Requires-Dist: isort>=5.8.0; extra == "dev"
Requires-Dist: flake8>=3.9.1; extra == "dev"
Requires-Dist: mypy>=0.812; extra == "dev"
Requires-Dist: pytest-cov>=2.12.0; extra == "dev"
